{
  "minecraft:recipes/combat/wooden_sword": {
    "criteria": {
      "has_stick": "2021-07-19 09:06:32 -0400"
    },
    "done": true
  },
  "minecraft:recipes/redstone/wooden_button": {
    "criteria": {
      "has_planks": "2021-07-19 09:07:01 -0400"
    },
    "done": true
  },
  "minecraft:recipes/tools/wooden_axe": {
    "criteria": {
      "has_stick": "2021-07-19 09:06:32 -0400"
    },
    "done": true
  },
  "minecraft:recipes/building_blocks/brick_stairs": {
    "criteria": {
      "has_brick_block": "2021-07-19 08:54:54 -0400"
    },
    "done": true
  },
  "minecraft:recipes/building_blocks/oak_wooden_slab": {
    "criteria": {
      "has_planks": "2021-07-19 09:07:01 -0400"
    },
    "done": true
  },
  "minecraft:recipes/decorations/fence": {
    "criteria": {
      "has_planks": "2021-07-19 09:07:01 -0400"
    },
    "done": true
  },
  "minecraft:recipes/building_blocks/brick_slab": {
    "criteria": {
      "has_brick_block": "2021-07-19 08:54:54 -0400"
    },
    "done": true
  },
  "minecraft:recipes/tools/wooden_hoe": {
    "criteria": {
      "has_stick": "2021-07-19 09:06:32 -0400"
    },
    "done": true
  },
  "enderio:root": {
    "criteria": {
      "location": "2021-07-19 08:54:31 -0400"
    },
    "done": true
  },
  "cfm:root": {
    "criteria": {
      "tick": "2021-07-19 08:54:31 -0400"
    },
    "done": true
  },
  "minecraft:adventure/adventuring_time": {
    "criteria": {
      "plains": "2021-07-19 08:54:31 -0400"
    },
    "done": false
  },
  "minecraft:recipes/decorations/crafting_table": {
    "criteria": {
      "has_planks": "2021-07-19 09:07:01 -0400"
    },
    "done": true
  },
  "minecraft:recipes/tools/wooden_pickaxe": {
    "criteria": {
      "has_stick": "2021-07-19 09:06:32 -0400"
    },
    "done": true
  },
  "minecraft:recipes/redstone/trapdoor": {
    "criteria": {
      "has_planks": "2021-07-19 09:07:01 -0400"
    },
    "done": true
  },
  "minecraft:recipes/decorations/ladder": {
    "criteria": {
      "has_stick": "2021-07-19 09:06:32 -0400"
    },
    "done": true
  },
  "minecraft:recipes/decorations/chest": {
    "criteria": {
      "has_lots_of_items": "2021-07-19 09:02:43 -0400"
    },
    "done": true
  },
  "minecraft:recipes/building_blocks/oak_stairs": {
    "criteria": {
      "has_planks": "2021-07-19 09:07:01 -0400"
    },
    "done": true
  },
  "cfm:install": {
    "criteria": {
      "tick": "2021-07-19 08:54:31 -0400"
    },
    "done": true
  },
  "minecraft:recipes/tools/wooden_shovel": {
    "criteria": {
      "has_stick": "2021-07-19 09:06:32 -0400"
    },
    "done": true
  },
  "minecraft:recipes/redstone/fence_gate": {
    "criteria": {
      "has_planks": "2021-07-19 09:07:01 -0400"
    },
    "done": true
  },
  "minecraft:recipes/redstone/wooden_pressure_plate": {
    "criteria": {
      "has_planks": "2021-07-19 09:07:01 -0400"
    },
    "done": true
  },
  "galacticraftcore:galacticraft/root": {
    "criteria": {
      "tick": "2021-07-19 08:54:31 -0400"
    },
    "done": true
  },
  "progressiveautomation:coal_pellets": {
    "criteria": {
      "has_coal": "2021-07-19 09:03:06 -0400"
    },
    "done": true
  },
  "minecraft:recipes/misc/stick": {
    "criteria": {
      "has_planks": "2021-07-19 09:07:01 -0400"
    },
    "done": true
  },
  "minecraft:recipes/redstone/wooden_door": {
    "criteria": {
      "has_planks": "2021-07-19 09:07:01 -0400"
    },
    "done": true
  },
  "minecraft:recipes/decorations/sign": {
    "criteria": {
      "has_planks": "2021-07-19 09:07:01 -0400"
    },
    "done": true
  }
}